{
  "CONCEJO DELIBERANTE": {
    "Concejo Deliberante": 107627639
  },
  "INTEDENCIA": {
    "Intendencia": 14.56,
    "Juzgado de Faltas": 22.27,
    "Dir. Asuntos Legales": 14.73,
    "Dir. Comunicaciones": 14.78,
    "Dir. Modernizaci칩n": 22.75,
    "Protocolo y Ceremonial": 7.85,
    "Dir. Gestion y Articulacion": 3.06
  },
  "GOBIERNO": {
    "Secretaria Gobierno": 7.35,
    "Dir. Recursos Humanos": 7.73,
    "Dir. Prevecion y Seguridad": 37.85,
    "Dir. Gestion Cultural": 16.85,
    "por corregir - Rel.Institucional": 9.87,
    "Dir. Juventud": 3.64,
    "Gerencia Choferes": 6.60,
    "Dir. Educacion": 2.91,
    "Dir. Deporte": 7.19
  },
  "PLANIFICACION": {
    "Dir. Dise침o y Planificacion Terr": 12.13,
    "Ente Reg, Serv. Concesionados": 6.82,
    "Dir. Obras Particulares": 13.72,
    "Dir. Planeamiento y Catastro": 2.40,
    "por corregir - Planif.y gesti칩n urbana": 2.84,
    "por corregir - Obras Municipales": 62.09
  },
  "ESPACIOS PUBLICOS": {
    "Secretaria Obras Publicas": 18.92,
    "por corregir - Des. Sustentab": 3.45,
    "Dir. Servicios Publicos": 34.04,
    "Dir. Arbolado y Parques": 12.28,
    "Gestion Ambiental": 2.41,
    "Dir. Zoonosis y Vectores": 3.34,
    "R.R.U": 3.23,
    "Dir. Girsu": 22.32
  },
  "DESARROLLO SOCIAL": {
    "Sec. Desarrollo Social": 35.60,
    "Dir. Familia": 18.55,
    "Centros Des. Infantil": 15.68,
    "Coord. Centros Des Territorial": 19.42,
    "Dir. Unidad Local Ni침ez": 8.27,
    "Dir. Politicas de Genero": 2.48
  },
  "ECONOMIA": {
    "Sec. Economia": 6.03,
    "Contaduria General": 15.98,
    "Dir. Rentas": 20.41,
    "Dir. Hab y Control Comercial": 21.35,
    "Dir. Desarrollo Econ y Prod": 24.72,
    "Tesoreria": 11.51
  },
  "ORGANISMOS DESCENTRALIZADOS": {
    "Org. Desc. Caminos Vecinales": 238541328.30,
    "Org. Desc. Planta Asfalto": 679519361.50
  },
  "NO PROGRAMATICO": {
    "Partidas No Programaticas": 8322630674.68
  }
}
